BiliOpen/__init__.py
BiliOpen/__main__.py
BiliOpen/api.py
BiliOpen/bilibili.py
biliopen-2.0.1.dist-info/LICENSE
biliopen-2.0.1.dist-info/METADATA
biliopen-2.0.1.dist-info/WHEEL
biliopen-2.0.1.dist-info/entry_points.txt
biliopen-2.0.1.dist-info/top_level.txt
biliopen-2.0.1.dist-info/RECORD
