Metadata-Version: 2.1
Name: BiliOpen
Version: 2.0.1
Summary: ☁️ 哔哩开放云，支持任意文件的全速上传与下载
Home-page: https://github.com/Wodlie/BiliOpen
Author: Hsury & Wodlie
Author-email: i@hsury.com
Keywords: bilibili,cloud,disk,drive,storage,pan,yun,B站,哔哩哔哩,网盘
Classifier: Development Status :: 4 - Beta
Classifier: Environment :: Console
Classifier: Intended Audience :: Developers
Classifier: Intended Audience :: End Users/Desktop
Classifier: License :: OSI Approved :: MIT License
Classifier: Natural Language :: Chinese (Simplified)
Classifier: Natural Language :: English
Classifier: Operating System :: OS Independent
Classifier: Programming Language :: Python :: 3.7
Classifier: Topic :: Communications :: File Sharing
Classifier: Topic :: Internet :: WWW/HTTP
Classifier: Topic :: Utilities
Requires-Python: >=3.6
License-File: LICENSE
Requires-Dist: requests
Requires-Dist: Pillow
Requires-Dist: numpy
